safecatch/___init__.py
safecatch/multi_safecatch.py
safecatch/safecatch.py
safecatch-1.0.3.dist-info/METADATA
safecatch-1.0.3.dist-info/WHEEL
safecatch-1.0.3.dist-info/top_level.txt
safecatch-1.0.3.dist-info/RECORD
