Metadata-Version: 2.1
Name: safecatch
Version: 1.0.3
Summary: A python package that allows you to handle exceptions easily
Author-email: Q12 <qque12euqq@gmail.com>
Project-URL: Homepage, https://github.com/pypa/sampleproject
Project-URL: Issues, https://github.com/pypa/sampleproject/issues
Classifier: Programming Language :: Python :: 3
Classifier: Operating System :: OS Independent
Classifier: License :: OSI Approved :: MIT License
Requires-Python: >=3.8
